<?xml version="1.0" encoding="utf-8"?>
<resources>
  <string name="menu_io">Importar / Exportar</string>
  <string name="menu_lang">Idioma</string>
  <string name="menu_about">Acerca de</string>
  <string name="btn_freeze">Activar Todo</string>
  <string name="btn_revert">Restaurar Todo</string>
  <string name="btn_reapply">Forzar Reaplicación</string>
  <string name="sec_tweaks">Ajustes del Sistema (System Tweaks)</string>
  <string name="tgl_kernel">Kernel Tweaks</string>
  <string name="tgl_kernel_desc">Acelera el cambio de tareas y reduce los despertares innecesarios del CPU</string>
  <string name="tgl_sysprops">System Props</string>
  <string name="tgl_sysprops_desc">Desactiva el registro de depuración, ahorrando batería y RAM</string>
  <string name="tgl_blur">Desactivar Desenfoque (Blur)</string>
  <string name="tgl_blur_desc">Reduce la carga gráfica (GPU), otorgando mayor fluidez en dispositivos de gama baja</string>
  <string name="tgl_logs">Detener Logs (Kill Logs)</string>
  <string name="tgl_logs_desc">Detiene procesos de registro en segundo plano para liberar RAM</string>
  <string name="reboot_req">⚠ Requiere reinicio</string>
  <string name="tgl_tracking">Bloquear rastreo de Google</string>
  <string name="tgl_tracking_desc">Desactiva las analíticas de GMS, telemetría Clearcut, sondeo de Phenotype y rastreo de anuncios a nivel de aplicación</string>
  <string name="sec_doze">Modo Doze (Suspensión)</string>
  <string name="tgl_gms_doze">GMS Doze</string>
  <string name="tgl_gms_doze_desc">Permite al sistema optimizar el consumo de batería de GMS · Puede retrasar notificaciones</string>
  <string name="tgl_cad">Doze Personalizado</string>
  <string name="tgl_cad_desc">Elimina las aplicaciones seleccionadas de la lista de excepciones de ahorro de energía (Doze)</string>
  <string name="cad_btn">▶ Administrar Apps</string>
  <string name="cad_title">Doze Personalizado</string>
  <string name="cad_notice">Las aplicaciones seleccionadas se eliminarán de la lista de excepciones de Doze para que el sistema pueda optimizarlas. Solo se muestran las aplicaciones que actualmente omiten la optimización de batería.</string>
  <string name="cad_search">Buscar aplicaciones...</string>
  <string name="cad_loading">Cargando...</string>
  <string name="cad_empty">No se encontraron aplicaciones</string>
  <string name="cad_sep_added">Ya añadidas</string>
  <string name="cad_warn_gms">GMS Doze ya se encarga de esto. Usa el interruptor de GMS Doze en su lugar.</string>
  <string name="cad_warn_system">⚠ Este paquete es requerido por el sistema y no se puede añadir</string>
  <string name="loading_applying_cad">Aplicando Doze Personalizado...</string>
  <string name="loading_reverting_cad">Revirtiendo Doze Personalizado...</string>
  <string name="log_cad_applied">Doze Personalizado aplicado</string>
  <string name="log_cad_reverted">Doze Personalizado revertido</string>
  <string name="log_cad_reapplied">Doze Personalizado reaplicado</string>
  <string name="tgl_deep_doze">Deep Doze (Suspensión Profunda)</string>
  <string name="tgl_deep_doze_desc">Aplica restricciones drásticas en la actividad en segundo plano de todas las aplicaciones</string>
  <string name="lvl_moderate">Moderado</string>
  <string name="lvl_maximum">Máximo</string>
  <string name="wl_btn">▶Lista Blanca (Whitelist) de Doze</string>
  <string name="sec_gms">Categorías GMS</string>
  <string name="cat_telemetry">Telemetría (Telemetry)</string>
  <string name="cat_telemetry_tag">Seguro · Anuncios, estadísticas, rastreo</string>
  <string name="cat_background">Segundo Plano (Background)</string>
  <string name="cat_background_tag">Seguro · Actualizaciones, MDM</string>
  <string name="cat_location">Ubicación (Location)</string>
  <string name="cat_location_tag">Desactiva Google Maps, GPS y Buscar mi dispositivo</string>
  <string name="cat_connectivity">Conectividad (Connectivity)</string>
  <string name="cat_connectivity_tag">Desactiva Chromecast, Quick Share y Fast Pair</string>
  <string name="cat_cloud">Nube (Cloud)</string>
  <string name="cat_cloud_tag">Desactiva inicio de sesión en Google, contraseñas y autocompletado</string>
  <string name="cat_payments">Pagos (Payments)</string>
  <string name="cat_payments_tag">Desactiva Google Pay y pagos por NFC</string>
  <string name="cat_wearables">Wearables (Relojes/Fitness)</string>
  <string name="cat_wearables_tag">Desactiva Wear OS y Google Fit</string>
  <string name="cat_games">Juegos (Games)</string>
  <string name="cat_games_tag">Desactiva Play Games y el guardado en la nube</string>
  <string name="sec_log">Registro de Actividad</string>
  <string name="wl_title">Lista Blanca (Whitelist) de Doze</string>
  <string name="wl_notice">Las aplicaciones agregadas aquí omitirán las restricciones del Deep Doze. Añade tus aplicaciones de mensajería, bancos y alarmas aquí.</string>
  <string name="wl_search">Buscar aplicaciones...</string>
  <string name="wl_system">Sistema</string>
  <string name="wl_loading">Cargando aplicaciones...</string>
  <string name="wl_empty">No se encontraron aplicaciones</string>
  <string name="wl_sep_other">Otras aplicaciones</string>
  <string name="io_title">Importar / Exportar</string>
  <string name="io_export">Exportar Configuración Actual</string>
  <string name="io_backups">Copias de seguridad guardadas</string>
  <string name="io_empty">No hay copias de seguridad</string>
  <string name="io_loading">Cargando...</string>
  <string name="io_error">Error al cargar las copias de seguridad</string>
  <string name="about_github">Ver proyecto en GitHub</string>
  <string name="lang_title">Idioma</string>
  <string name="loading_default">Procesando...</string>
  <string name="loading_enabling">Activando...</string>
  <string name="loading_disabling">Desactivando...</string>
  <string name="loading_freezing">Congelando...</string>
  <string name="loading_unfreezing">Descongelando...</string>
  <string name="loading_applying_kernel">Aplicando Kernel Tweaks...</string>
  <string name="loading_reverting_kernel">Revirtiendo configuraciones del kernel...</string>
  <string name="loading_applying_blur">Aplicando ajustes de desenfoque (Blur)...</string>
  <string name="loading_killing_logs">Deteniendo logs del sistema...</string>
  <string name="loading_applying_tracking">Bloqueando rastreo de Google...</string>
  <string name="loading_reverting_tracking">Revirtiendo bloqueo de rastreo de Google...</string>
  <string name="loading_applying_sysprops">Activando System Props...</string>
  <string name="loading_disabling_sysprops">Desactivando System Props...</string>
  <string name="loading_applying_gms_doze">Aplicando GMS Doze...</string>
  <string name="loading_reverting_gms_doze">Revirtiendo GMS Doze...</string>
  <string name="loading_applying_deep_doze">Aplicando Deep Doze...</string>
  <string name="loading_reverting_deep_doze">Revirtiendo Deep Doze...</string>
  <string name="loading_enabling_all">Activando todas las configuraciones...</string>
  <string name="loading_enabling_toggles">Activando todos los interruptores...</string>
  <string name="loading_freezing_cats">Congelando categorías GMS...</string>
  <string name="loading_freezing_services">Congelando servicios GMS individualmente...</string>
  <string name="loading_reverting_all">Restaurando todo por defecto...</string>
  <string name="loading_disabling_toggles">Desactivando todos los interruptores...</string>
  <string name="loading_disabling_cats">Desactivando todas las categorías GMS...</string>
  <string name="loading_restoring_kernel">Restaurando valores originales del kernel...</string>
  <string name="loading_re_enabling_gms">Reactivando servicios GMS...</string>
  <string name="loading_restoring_blur">Restaurando desenfoque (Blur)...</string>
  <string name="loading_reapplying_deep">Reaplicando modo Deep Doze...</string>
  <string name="loading_setting_level">Configurando nivel de Doze...</string>
  <string name="loading_reapplying">Reaplicando configuración...</string>
  <string name="toast_frozen">Todo ha sido congelado y aplicado con éxito</string>
  <string name="toast_reverted">Todo ha sido revertido a sus valores predeterminados</string>
  <string name="toast_refreshed">Actualizado correctamente</string>
  <string name="toast_reapplied">Configuración reaplicada con éxito</string>
  <string name="toast_exported">Guardado exitosamente</string>
  <string name="toast_export_failed">Error al exportar</string>
  <string name="toast_imported">¡Importado! Por favor, reinicia o reaplica tus ajustes</string>
  <string name="toast_import_failed">Error al importar</string>
  <string name="toast_log_copied">Registro copiado al portapapeles</string>
  <string name="toast_copy_failed">Error al copiar</string>
  <string name="toast_error">Ocurrió un error</string>
  <string name="ksu_unavailable_title">API de KSU no disponible</string>
  <string name="ksu_unavailable_desc">Esta interfaz WebUI requiere KernelSU. Si usas Magisk o APatch, utiliza el botón Action de tu administrador o la aplicación WebUI-X.</string>
  <string name="toast_on">ACTIVADO</string>
  <string name="toast_off">DESACTIVADO</string>
  <string name="toast_cat_frozen">congelado</string>
  <string name="toast_cat_restored">restaurado</string>
  <string name="toast_rename_failed">Error al intentar renombrar</string>
  <string name="log_kernel_applied">Kernel: {0} aplicados, {1} fallidos/no encontrados, {2} omitidos</string>
  <string name="log_kernel_restored">Kernel: {0} valores restaurados</string>
  <string name="log_kernel_vals_restored">Kernel: {0} valores restaurados con éxito</string>
  <string name="log_killed_logs">{0} procesos de log han sido detenidos</string>
  <string name="log_tracking_applied">Rastreo de Google bloqueado</string>
  <string name="log_tracking_reverted">Bloqueo de rastreo de Google revertido</string>
  <string name="log_sysprops_failed">Error al aplicar System Props: {0}</string>
  <string name="log_blur_state">Desenfoque (Blur): {0}</string>
  <string name="log_blur_restored">El desenfoque ha sido restaurado por defecto</string>
  <string name="log_gms_doze_applied">Modo GMS Doze activado y aplicado</string>
  <string name="log_gms_doze_reverted">Modo GMS Doze desactivado y revertido</string>
  <string name="log_deep_doze_applied">Modo Deep Doze activado y aplicado</string>
  <string name="log_deep_doze_reverted">Modo Deep Doze desactivado y revertido</string>
  <string name="log_deep_doze_level">Deep Doze configurado en nivel → {0}</string>
  <string name="log_deep_doze_reapplied">Modo Deep Doze reaplicado</string>
  <string name="log_toggles_enabled">Todos los interruptores del sistema se han activado</string>
  <string name="log_toggles_disabled">Todos los interruptores del sistema se han desactivado</string>
  <string name="log_cats_enabled">Todas las categorías GMS se han activado</string>
  <string name="log_cats_disabled">Todas las categorías GMS se han desactivado</string>
  <string name="log_cat_frozen">{0}: {1} servicios desactivados, {2} fallidos</string>
  <string name="log_cat_restored">{0}: {1} servicios reactivados, {2} fallidos</string>
  <string name="log_gms_frozen">GMS: {0} desactivados, {1} reactivados, {2} fallidos</string>
  <string name="log_gms_restored">GMS: {0} reactivados, {1} fallidos</string>
  <string name="log_toggle_on">{0} se ha activado</string>
  <string name="log_toggle_off">{0} se ha desactivado</string>
  <string name="log_webui_ready">La interfaz WebUI está lista</string>
  <string name="log_load_failed">Fallo de carga: {0}</string>
  <string name="log_reboot_effect">Reinicia el dispositivo para obtener el efecto completo</string>
  <string name="log_reverting_all">Restaurando toda la configuración por defecto...</string>
  <string name="log_freeze_all">Activando toda la configuración...</string>
  <string name="word_enabled">activado</string>
  <string name="word_disabled">desactivado</string>
  <string name="toast_nothing_to_apply">No hay nada que aplicar — por favor activa alguna opción primero</string>
  <string name="about_desc">Máximo ahorro de batería y optimización de GMS. Congela servicios GMS, activa Doze, detén logs y aplica Kernel Tweaks. Usa el botón WebUI para editar la configuración.</string>
  <string name="log_sysprops_enabled">System Props activados</string>
  <string name="log_sysprops_disabled">System Props desactivados</string>
  <string name="log_reapply_start">Iniciando reaplicación...</string>
  <string name="log_empty">Sin actividad todavía</string>
  <string name="tgl_ram_optimizer">Optimizador de RAM</string>
  <string name="tgl_ram_optimizer_desc">Limita los procesos en caché y vacíos en segundo plano, ajusta el swap de zram para liberar más RAM</string>
  <string name="log_ram_applied">Optimizador de RAM aplicado</string>
  <string name="log_ram_reverted">Optimizador de RAM revertido</string>
  <string name="loading_applying_ram">Aplicando optimizador de RAM...</string>
  <string name="loading_reverting_ram">Revirtiendo optimizador de RAM...</string>
  <string name="tgl_bss">Optimizador de Ahorro de Batería</string>
  <string name="tgl_bss_desc">Ajusta el comportamiento del modo de ahorro de energía nativo de Android</string>
  <string name="loading_applying_bss">Aplicando perfil de Ahorro de Batería...</string>
  <string name="loading_reverting_bss">Revirtiendo Ahorro de Batería...</string>
  <string name="log_bss_applied">Perfil de ahorro de energía aplicado</string>
  <string name="log_bss_reverted">Ahorro de energía revertido</string>
  <string name="log_bss_reapplied">Ahorro de energía reaplicado</string>
  <string name="bss_modal_title">Opciones de Ahorro de Batería</string>
  <string name="bss_modal_notice">Los ajustes tienen efecto mientras el Ahorro de Batería está activo.</string>
  <string name="bss_configure">Configurar Opciones</string>
  <string name="bss_opt_hotword">Desactivar detección de voz</string>
  <string name="bss_opt_hotword_desc">Evita que el micrófono esté siempre escuchando "Hey Google".</string>
  <string name="bss_opt_fullbackup">Aplazar copias de seguridad completas</string>
  <string name="bss_opt_fullbackup_desc">Pausa los backups completos del dispositivo mientras el ahorro está activo.</string>
  <string name="bss_opt_keybackup">Aplazar backups de datos</string>
  <string name="bss_opt_keybackup_desc">Pausa la sincronización de configuraciones de apps a la nube.</string>
  <string name="bss_opt_force_standby">Forzar suspensión de apps</string>
  <string name="bss_opt_force_standby_desc">Mueve las apps en segundo plano al grupo restringido, limitando drásticamente sus despertares.</string>
  <string name="bss_opt_force_bg">Forzar revisión en segundo plano</string>
  <string name="bss_opt_force_bg_desc">Aplica restricciones más estrictas a la ejecución en segundo plano para todas las aplicaciones.</string>
  <string name="bss_opt_sensors">Desactivar sensores opcionales</string>
  <string name="bss_opt_sensors_desc">Apaga sensores no críticos como el barómetro, el contador de pasos y el vector de rotación.</string>
  <string name="bss_opt_gps">Modo de ubicación</string>
  <string name="bss_apply">Aplicar y Cerrar</string>
  <string name="bss_gps_0">Sin restricciones</string>
  <string name="bss_gps_1">GPS apagado (pantalla off)</string>
  <string name="bss_gps_2">Todo apagado (pantalla off)</string>
  <string name="bss_gps_3">Solo primer plano</string>
  <string name="bss_gps_4">Limitado (pantalla off)</string>
  <string name="bss_gps_hint_0">El GPS y los servicios de ubicación funcionan normalmente en todo momento.</string>
  <string name="bss_gps_hint_1">El chip GPS se apaga cuando la pantalla se apaga. La ubicación por Wi-Fi y redes móviles continúa funcionando con menor precisión.</string>
  <string name="bss_gps_hint_2">Todos los proveedores de ubicación (GPS, Wi-Fi, red) se detienen al apagar la pantalla. Los widgets del clima y rastreadores no se actualizan en segundo plano.</string>
  <string name="bss_gps_hint_3">Solo la aplicación en pantalla puede acceder a la ubicación. Las aplicaciones en segundo plano son totalmente bloqueadas.</string>
  <string name="bss_gps_hint_4">Las apps en segundo plano aún pueden obtener la ubicación, pero con actualizaciones limitadas cuando la pantalla está apagada.</string>
  <string name="io_btn_import">Importar</string>
  <string name="io_btn_delete">Eliminar</string>
  <string name="io_btn_rename">Renombrar</string>
  <string name="io_rename_prompt">Renombrar copia:</string>
  <string name="bss_opt_datasaver">Activar ahorro de datos</string>
  <string name="bss_opt_datasaver_desc">Restringe el uso de datos en segundo plano para todas las aplicaciones mientras el ahorro de batería está activo</string>
</resources>